src/LICENSE
src/__init__.py
src/config.py
src/graph.py
src/models.py
src/prompts.py
src/server.py
src/state.py
src/utils.py
mseep_gemini_lg_mcp-0.1.1.dist-info/METADATA
mseep_gemini_lg_mcp-0.1.1.dist-info/WHEEL
mseep_gemini_lg_mcp-0.1.1.dist-info/entry_points.txt
mseep_gemini_lg_mcp-0.1.1.dist-info/licenses/LICENSE
mseep_gemini_lg_mcp-0.1.1.dist-info/RECORD
