Metadata-Version: 2.4
Name: mseep-gemini-lg-mcp
Version: 0.1.1
Summary: Gemini-powered research agent MCP server
Author-email: mseep <support@skydeck.ai>
License: MIT
License-File: LICENSE
Keywords: ai,gemini,mcp,research,search
Classifier: Development Status :: 4 - Beta
Classifier: Intended Audience :: Developers
Classifier: License :: OSI Approved :: MIT License
Classifier: Programming Language :: Python :: 3
Classifier: Programming Language :: Python :: 3.10
Classifier: Programming Language :: Python :: 3.11
Classifier: Programming Language :: Python :: 3.12
Requires-Python: >=3.10
Requires-Dist: google-genai>=0.3.0
Requires-Dist: langchain-core>=0.3.0
Requires-Dist: langchain-google-genai>=2.0.0
Requires-Dist: langchain>=0.3.0
Requires-Dist: langgraph>=0.2.0
Requires-Dist: mcp[cli]>=1.0.0
Requires-Dist: pydantic>=2.0.0
Requires-Dist: python-dotenv>=1.0.0
Requires-Dist: requests>=2.31.0
